{
  "id": "4563ad1f-84d1-47d5-a7ac-f159ba59b3e7",
  "name": "Monstera Deliciosa",
  "category": "nature",
  "tags": [
    "pirate",
    "paradise",
    "pirates",
    "nature",
    "fern",
    "beach",
    "foliage",
    "plant",
    "plants",
    "botanical",
    "damage",
    "decay",
    "flora",
    "hole",
    "leaf",
    "leafy",
    "monstera",
    "natural",
    "organic"
  ],
  "caption": "Monstera leaf with a hole.",
  "author": "Decentraland Foundation",
  "boundingBox": {
    "x": 1.173,
    "y": 1.714,
    "z": 1.116
  }
}
