{
  "id": "91066396-ce04-4d83-abbc-8502520ce8cb",
  "name": "Skull&Candles ",
  "category": "decorations",
  "tags": [
    "ammo",
    "bullet",
    "candle",
    "candlestick",
    "combat",
    "eerie",
    "firearm",
    "funeral",
    "grave",
    "gun",
    "macabre",
    "relic",
    "rifle",
    "shooting",
    "skull"
  ],
  "caption": "Skull with glowing candle beside a gun.",
  "author": "Decentraland Foundation",
  "boundingBox": {
    "x": 1.007,
    "y": 0.827,
    "z": 0.805
  }
}
